demo.py
test_termformatters.py
termformatters/__init__.py
termformatters/base.py
termformatters-0.2.1.dist-info/LICENSE
termformatters-0.2.1.dist-info/METADATA
termformatters-0.2.1.dist-info/WHEEL
termformatters-0.2.1.dist-info/top_level.txt
termformatters-0.2.1.dist-info/RECORD
