Metadata-Version: 2.1
Name: termformatters
Version: 0.2.1
Summary: Terminal font style and base 16 colors formatters
Author-email: Alex Marienko <alexey.maryenko@gmail.com>
License: MIT License        
Project-URL: Homepage, https://github.com/amarienko/TerminalFormatters
Project-URL: Bug Tracker, https://github.com/amarienko/TerminalFormatters/issues
Keywords: terminal,font,colors,styles,formatter
Classifier: Programming Language :: Python :: 3
Classifier: Programming Language :: Python :: 3.9
Classifier: Programming Language :: Python :: 3.10
Classifier: Programming Language :: Python :: 3 :: Only
Classifier: Environment :: Console
Classifier: Development Status :: 5 - Production/Stable
Classifier: License :: OSI Approved :: MIT License
Classifier: Natural Language :: English
Classifier: Operating System :: OS Independent
Classifier: Operating System :: POSIX
Classifier: Operating System :: POSIX :: Linux
Classifier: Operating System :: POSIX :: Other
Classifier: Operating System :: POSIX :: BSD
Classifier: Operating System :: Unix
Classifier: Operating System :: MacOS
Classifier: Operating System :: MacOS :: MacOS X
Requires-Python: >=3.9
License-File: LICENSE
